{
  "logoType": "lucideIcon",
  "logo": {
    "lucideIcon": "code",
    "imagePath": "",
    "imageLink": ""
  },
  "logoScale": 1.2,
  "iconColorType": "default",
  "wordmark": "Hello World!",
  "customFont": "monospaceFont",
  "fontSize": "2em",
  "fontColorType": "default",
  "fontWeight": 600,
  "maxResults": 5,
  "showbookmarkedFiles": true,
  "showRecentFiles": false,
  "maxRecentFiles": 5,
  "storeRecentFile": true,
  "showPath": true,
  "selectionHighlight": "default",
  "showShortcuts": true,
  "markdownOnly": false,
  "unresolvedLinks": false,
  "recentFilesStore": [
    {
      "filepath": "04 - Matriz/Tipos de Matrizes.md",
      "timestamp": 1749864378092
    },
    {
      "filepath": "04 - Matriz/Matriz.md",
      "timestamp": 1749864375920
    },
    {
      "filepath": "04 - Matriz/Ordem de uma Matriz.md",
      "timestamp": 1749864375236
    },
    {
      "filepath": "04 - Matriz/Elementos de uma Matriz.md",
      "timestamp": 1749864352711
    },
    {
      "filepath": "Welcome.md",
      "timestamp": 1749863815598
    }
  ],
  "bookmarkedFileStore": [],
  "searchDelay": 0,
  "replaceNewTabs": true,
  "newTabOnStart": false,
  "closePreviousSessionTabs": false,
  "omnisearch": false,
  "showOmnisearchExcerpt": true
}